jootranslate/__init__.py
jootranslate/cli.py
tests/__init__.py
tests/test_cli.py
jootranslate-1.1.0.dist-info/LICENSE.txt
jootranslate-1.1.0.dist-info/METADATA
jootranslate-1.1.0.dist-info/WHEEL
jootranslate-1.1.0.dist-info/entry_points.txt
jootranslate-1.1.0.dist-info/top_level.txt
jootranslate-1.1.0.dist-info/RECORD
