Metadata-Version: 2.1
Name: jootranslate
Version: 1.1.0
Summary: cli tool to generate translation files for joomla
Home-page: https://github.com/pfitzer/jtranslate.git
Author: Michael Pfister
Author-email: michael@mp-development.de
License: MIT
Keywords: joomla cli translations
Platform: UNKNOWN
Classifier: Development Status :: 5 - Production/Stable
Classifier: License :: OSI Approved :: MIT License
Classifier: Environment :: Console
Classifier: Intended Audience :: Developers
Classifier: Programming Language :: Python
Classifier: Programming Language :: Python :: 3
Classifier: Programming Language :: Python :: 3 :: Only
Classifier: Programming Language :: Python :: 3.6
Classifier: Programming Language :: Python :: 3.7
Classifier: Topic :: Software Development :: Localization
Requires-Dist: configobj
